[
  {
    "category": "drivers",
    "title": "Most Race Wins",
    "entries": [
      {
        "rank": 1,
        "driverId": "lewis-hamilton",
        "value": 105
      },
      {
        "rank": 2,
        "driverId": "michael-schumacher",
        "value": 91
      },
      {
        "rank": 3,
        "driverId": "max-verstappen",
        "value": 71
      },
      {
        "rank": 4,
        "driverId": "sebastian-vettel",
        "value": 53
      },
      {
        "rank": 5,
        "driverId": "alain-prost",
        "value": 51
      },
      {
        "rank": 6,
        "driverId": "ayrton-senna",
        "value": 41
      },
      {
        "rank": 7,
        "driverId": "fernando-alonso",
        "value": 32
      },
      {
        "rank": 8,
        "driverId": "nigel-mansell",
        "value": 31
      },
      {
        "rank": 9,
        "driverId": "jackie-stewart",
        "value": 27
      },
      {
        "rank": 10,
        "driverId": "jim-clark",
        "value": 25
      },
      {
        "rank": 11,
        "driverId": "niki-lauda",
        "value": 25
      },
      {
        "rank": 12,
        "driverId": "juan-manuel-fangio",
        "value": 24
      },
      {
        "rank": 13,
        "driverId": "nelson-piquet",
        "value": 23
      },
      {
        "rank": 14,
        "driverId": "nico-rosberg",
        "value": 23
      },
      {
        "rank": 15,
        "driverId": "damon-hill",
        "value": 22
      },
      {
        "rank": 16,
        "driverId": "kimi-raikkonen",
        "value": 21
      },
      {
        "rank": 17,
        "driverId": "mika-hakkinen",
        "value": 20
      },
      {
        "rank": 18,
        "driverId": "stirling-moss",
        "value": 16
      },
      {
        "rank": 19,
        "driverId": "jenson-button",
        "value": 15
      },
      {
        "rank": 20,
        "driverId": "jack-brabham",
        "value": 14
      }
    ]
  },
  {
    "category": "drivers",
    "title": "Most Pole Positions",
    "entries": [
      {
        "rank": 1,
        "driverId": "lewis-hamilton",
        "value": 104
      },
      {
        "rank": 2,
        "driverId": "michael-schumacher",
        "value": 68
      },
      {
        "rank": 3,
        "driverId": "ayrton-senna",
        "value": 65
      },
      {
        "rank": 4,
        "driverId": "sebastian-vettel",
        "value": 57
      },
      {
        "rank": 5,
        "driverId": "max-verstappen",
        "value": 48
      },
      {
        "rank": 6,
        "driverId": "alain-prost",
        "value": 33
      },
      {
        "rank": 7,
        "driverId": "jim-clark",
        "value": 33
      },
      {
        "rank": 8,
        "driverId": "nigel-mansell",
        "value": 32
      },
      {
        "rank": 9,
        "driverId": "nico-rosberg",
        "value": 30
      },
      {
        "rank": 10,
        "driverId": "juan-manuel-fangio",
        "value": 29
      },
      {
        "rank": 11,
        "driverId": "charles-leclerc",
        "value": 27
      },
      {
        "rank": 12,
        "driverId": "mika-hakkinen",
        "value": 26
      },
      {
        "rank": 13,
        "driverId": "niki-lauda",
        "value": 24
      },
      {
        "rank": 14,
        "driverId": "nelson-piquet",
        "value": 24
      },
      {
        "rank": 15,
        "driverId": "fernando-alonso",
        "value": 22
      },
      {
        "rank": 16,
        "driverId": "damon-hill",
        "value": 20
      },
      {
        "rank": 17,
        "driverId": "valtteri-bottas",
        "value": 20
      },
      {
        "rank": 18,
        "driverId": "kimi-raikkonen",
        "value": 18
      },
      {
        "rank": 19,
        "driverId": "mario-andretti",
        "value": 18
      },
      {
        "rank": 20,
        "driverId": "rene-arnoux",
        "value": 18
      }
    ]
  },
  {
    "category": "drivers",
    "title": "Most Podium Finishes",
    "entries": [
      {
        "rank": 1,
        "driverId": "lewis-hamilton",
        "value": 202
      },
      {
        "rank": 2,
        "driverId": "michael-schumacher",
        "value": 155
      },
      {
        "rank": 3,
        "driverId": "max-verstappen",
        "value": 127
      },
      {
        "rank": 4,
        "driverId": "sebastian-vettel",
        "value": 122
      },
      {
        "rank": 5,
        "driverId": "alain-prost",
        "value": 106
      },
      {
        "rank": 6,
        "driverId": "fernando-alonso",
        "value": 106
      },
      {
        "rank": 7,
        "driverId": "kimi-raikkonen",
        "value": 103
      },
      {
        "rank": 8,
        "driverId": "ayrton-senna",
        "value": 80
      },
      {
        "rank": 9,
        "driverId": "rubens-barrichello",
        "value": 68
      },
      {
        "rank": 10,
        "driverId": "valtteri-bottas",
        "value": 67
      },
      {
        "rank": 11,
        "driverId": "david-coulthard",
        "value": 62
      },
      {
        "rank": 12,
        "driverId": "nelson-piquet",
        "value": 60
      },
      {
        "rank": 13,
        "driverId": "nigel-mansell",
        "value": 59
      },
      {
        "rank": 14,
        "driverId": "nico-rosberg",
        "value": 57
      },
      {
        "rank": 15,
        "driverId": "niki-lauda",
        "value": 54
      },
      {
        "rank": 16,
        "driverId": "mika-hakkinen",
        "value": 51
      },
      {
        "rank": 17,
        "driverId": "charles-leclerc",
        "value": 51
      },
      {
        "rank": 18,
        "driverId": "jenson-button",
        "value": 50
      },
      {
        "rank": 19,
        "driverId": "gerhard-berger",
        "value": 48
      },
      {
        "rank": 20,
        "driverId": "carlos-reutemann",
        "value": 45
      }
    ]
  },
  {
    "category": "drivers",
    "title": "Most Fastest Laps",
    "entries": [
      {
        "rank": 1,
        "driverId": "michael-schumacher",
        "value": 77
      },
      {
        "rank": 2,
        "driverId": "lewis-hamilton",
        "value": 68
      },
      {
        "rank": 3,
        "driverId": "kimi-raikkonen",
        "value": 46
      },
      {
        "rank": 4,
        "driverId": "alain-prost",
        "value": 41
      },
      {
        "rank": 5,
        "driverId": "sebastian-vettel",
        "value": 38
      },
      {
        "rank": 6,
        "driverId": "max-verstappen",
        "value": 37
      },
      {
        "rank": 7,
        "driverId": "nigel-mansell",
        "value": 30
      },
      {
        "rank": 8,
        "driverId": "jim-clark",
        "value": 28
      },
      {
        "rank": 9,
        "driverId": "fernando-alonso",
        "value": 26
      },
      {
        "rank": 10,
        "driverId": "mika-hakkinen",
        "value": 25
      },
      {
        "rank": 11,
        "driverId": "niki-lauda",
        "value": 24
      },
      {
        "rank": 12,
        "driverId": "juan-manuel-fangio",
        "value": 23
      },
      {
        "rank": 13,
        "driverId": "nelson-piquet",
        "value": 23
      },
      {
        "rank": 14,
        "driverId": "gerhard-berger",
        "value": 21
      },
      {
        "rank": 15,
        "driverId": "nico-rosberg",
        "value": 20
      },
      {
        "rank": 16,
        "driverId": "ayrton-senna",
        "value": 19
      },
      {
        "rank": 17,
        "driverId": "damon-hill",
        "value": 19
      },
      {
        "rank": 18,
        "driverId": "stirling-moss",
        "value": 19
      },
      {
        "rank": 19,
        "driverId": "valtteri-bottas",
        "value": 19
      },
      {
        "rank": 20,
        "driverId": "mark-webber",
        "value": 19
      }
    ]
  },
  {
    "category": "drivers",
    "title": "Most Championships",
    "entries": [
      {
        "rank": 1,
        "driverId": "lewis-hamilton",
        "value": 7
      },
      {
        "rank": 2,
        "driverId": "michael-schumacher",
        "value": 7
      },
      {
        "rank": 3,
        "driverId": "juan-manuel-fangio",
        "value": 5
      },
      {
        "rank": 4,
        "driverId": "max-verstappen",
        "value": 4
      },
      {
        "rank": 5,
        "driverId": "sebastian-vettel",
        "value": 4
      },
      {
        "rank": 6,
        "driverId": "alain-prost",
        "value": 4
      },
      {
        "rank": 7,
        "driverId": "ayrton-senna",
        "value": 3
      },
      {
        "rank": 8,
        "driverId": "jackie-stewart",
        "value": 3
      },
      {
        "rank": 9,
        "driverId": "niki-lauda",
        "value": 3
      },
      {
        "rank": 10,
        "driverId": "nelson-piquet",
        "value": 3
      },
      {
        "rank": 11,
        "driverId": "jack-brabham",
        "value": 3
      },
      {
        "rank": 12,
        "driverId": "fernando-alonso",
        "value": 2
      },
      {
        "rank": 13,
        "driverId": "jim-clark",
        "value": 2
      },
      {
        "rank": 14,
        "driverId": "mika-hakkinen",
        "value": 2
      },
      {
        "rank": 15,
        "driverId": "emerson-fittipaldi",
        "value": 2
      },
      {
        "rank": 16,
        "driverId": "graham-hill",
        "value": 2
      },
      {
        "rank": 17,
        "driverId": "alberto-ascari",
        "value": 2
      },
      {
        "rank": 18,
        "driverId": "nigel-mansell",
        "value": 1
      },
      {
        "rank": 19,
        "driverId": "nico-rosberg",
        "value": 1
      },
      {
        "rank": 20,
        "driverId": "damon-hill",
        "value": 1
      }
    ]
  },
  {
    "category": "drivers",
    "title": "Most Race Entries",
    "entries": [
      {
        "rank": 1,
        "driverId": "fernando-alonso",
        "value": 427
      },
      {
        "rank": 2,
        "driverId": "lewis-hamilton",
        "value": 381
      },
      {
        "rank": 3,
        "driverId": "kimi-raikkonen",
        "value": 350
      },
      {
        "rank": 4,
        "driverId": "rubens-barrichello",
        "value": 322
      },
      {
        "rank": 5,
        "driverId": "michael-schumacher",
        "value": 306
      },
      {
        "rank": 6,
        "driverId": "jenson-button",
        "value": 306
      },
      {
        "rank": 7,
        "driverId": "sebastian-vettel",
        "value": 299
      },
      {
        "rank": 8,
        "driverId": "sergio-perez",
        "value": 282
      },
      {
        "rank": 9,
        "driverId": "felipe-massa",
        "value": 269
      },
      {
        "rank": 10,
        "driverId": "daniel-ricciardo",
        "value": 257
      },
      {
        "rank": 11,
        "driverId": "riccardo-patrese",
        "value": 256
      },
      {
        "rank": 12,
        "driverId": "jarno-trulli",
        "value": 252
      },
      {
        "rank": 13,
        "driverId": "nico-hulkenberg",
        "value": 250
      },
      {
        "rank": 14,
        "driverId": "valtteri-bottas",
        "value": 247
      },
      {
        "rank": 15,
        "driverId": "david-coulthard",
        "value": 246
      },
      {
        "rank": 16,
        "driverId": "max-verstappen",
        "value": 234
      },
      {
        "rank": 17,
        "driverId": "carlos-sainz-jr",
        "value": 230
      },
      {
        "rank": 18,
        "driverId": "giancarlo-fisichella",
        "value": 229
      },
      {
        "rank": 19,
        "driverId": "mark-webber",
        "value": 215
      },
      {
        "rank": 20,
        "driverId": "gerhard-berger",
        "value": 210
      }
    ]
  },
  {
    "category": "drivers",
    "title": "Most Career Points",
    "entries": [
      {
        "rank": 1,
        "driverId": "lewis-hamilton",
        "value": 5030.5
      },
      {
        "rank": 2,
        "driverId": "max-verstappen",
        "value": 3452.5
      },
      {
        "rank": 3,
        "driverId": "sebastian-vettel",
        "value": 3098
      },
      {
        "rank": 4,
        "driverId": "fernando-alonso",
        "value": 2393
      },
      {
        "rank": 5,
        "driverId": "kimi-raikkonen",
        "value": 1873
      },
      {
        "rank": 6,
        "driverId": "valtteri-bottas",
        "value": 1797
      },
      {
        "rank": 7,
        "driverId": "charles-leclerc",
        "value": 1687
      },
      {
        "rank": 8,
        "driverId": "sergio-perez",
        "value": 1638
      },
      {
        "rank": 9,
        "driverId": "nico-rosberg",
        "value": 1594.5
      },
      {
        "rank": 10,
        "driverId": "michael-schumacher",
        "value": 1566
      },
      {
        "rank": 11,
        "driverId": "lando-norris",
        "value": 1440
      },
      {
        "rank": 12,
        "driverId": "carlos-sainz-jr",
        "value": 1336.5
      },
      {
        "rank": 13,
        "driverId": "daniel-ricciardo",
        "value": 1329
      },
      {
        "rank": 14,
        "driverId": "jenson-button",
        "value": 1235
      },
      {
        "rank": 15,
        "driverId": "felipe-massa",
        "value": 1167
      },
      {
        "rank": 16,
        "driverId": "george-russell",
        "value": 1058
      },
      {
        "rank": 17,
        "driverId": "mark-webber",
        "value": 1047.5
      },
      {
        "rank": 18,
        "driverId": "oscar-piastri",
        "value": 799
      },
      {
        "rank": 19,
        "driverId": "alain-prost",
        "value": 768.5
      },
      {
        "rank": 20,
        "driverId": "rubens-barrichello",
        "value": 658
      }
    ]
  },
  {
    "category": "drivers",
    "title": "Highest Win Rate (min 50 races)",
    "entries": [
      {
        "rank": 1,
        "driverId": "juan-manuel-fangio",
        "value": 0.471
      },
      {
        "rank": 2,
        "driverId": "jim-clark",
        "value": 0.347
      },
      {
        "rank": 3,
        "driverId": "max-verstappen",
        "value": 0.303
      },
      {
        "rank": 4,
        "driverId": "michael-schumacher",
        "value": 0.297
      },
      {
        "rank": 5,
        "driverId": "lewis-hamilton",
        "value": 0.276
      },
      {
        "rank": 6,
        "driverId": "jackie-stewart",
        "value": 0.273
      },
      {
        "rank": 7,
        "driverId": "alain-prost",
        "value": 0.256
      },
      {
        "rank": 8,
        "driverId": "ayrton-senna",
        "value": 0.255
      },
      {
        "rank": 9,
        "driverId": "stirling-moss",
        "value": 0.242
      },
      {
        "rank": 10,
        "driverId": "damon-hill",
        "value": 0.191
      },
      {
        "rank": 11,
        "driverId": "sebastian-vettel",
        "value": 0.177
      },
      {
        "rank": 12,
        "driverId": "nigel-mansell",
        "value": 0.166
      },
      {
        "rank": 13,
        "driverId": "niki-lauda",
        "value": 0.146
      },
      {
        "rank": 14,
        "driverId": "oscar-piastri",
        "value": 0.129
      },
      {
        "rank": 15,
        "driverId": "mika-hakkinen",
        "value": 0.124
      },
      {
        "rank": 16,
        "driverId": "nelson-piquet",
        "value": 0.113
      },
      {
        "rank": 17,
        "driverId": "nico-rosberg",
        "value": 0.112
      },
      {
        "rank": 18,
        "driverId": "jack-brabham",
        "value": 0.111
      },
      {
        "rank": 19,
        "driverId": "james-hunt",
        "value": 0.109
      },
      {
        "rank": 20,
        "driverId": "alan-jones",
        "value": 0.103
      }
    ]
  },
  {
    "category": "constructors",
    "title": "Most Constructor Wins",
    "entries": [
      {
        "rank": 1,
        "teamId": "ferrari",
        "value": 248
      },
      {
        "rank": 2,
        "teamId": "mclaren",
        "value": 203
      },
      {
        "rank": 3,
        "teamId": "mercedes",
        "value": 132
      },
      {
        "rank": 4,
        "teamId": "red-bull",
        "value": 130
      },
      {
        "rank": 5,
        "teamId": "williams",
        "value": 114
      },
      {
        "rank": 6,
        "teamId": "lotus",
        "value": 79
      },
      {
        "rank": 7,
        "teamId": "brabham",
        "value": 35
      },
      {
        "rank": 8,
        "teamId": "renault",
        "value": 35
      },
      {
        "rank": 9,
        "teamId": "benetton",
        "value": 27
      },
      {
        "rank": 10,
        "teamId": "tyrrell",
        "value": 23
      },
      {
        "rank": 11,
        "teamId": "brm",
        "value": 17
      },
      {
        "rank": 12,
        "teamId": "cooper",
        "value": 16
      },
      {
        "rank": 13,
        "teamId": "alfa-romeo",
        "value": 10
      },
      {
        "rank": 14,
        "teamId": "ligier",
        "value": 9
      },
      {
        "rank": 15,
        "teamId": "maserati",
        "value": 9
      },
      {
        "rank": 16,
        "teamId": "matra",
        "value": 9
      },
      {
        "rank": 17,
        "teamId": "vanwall",
        "value": 9
      },
      {
        "rank": 18,
        "teamId": "brawn",
        "value": 8
      },
      {
        "rank": 19,
        "teamId": "kurtis-kraft",
        "value": 5
      },
      {
        "rank": 20,
        "teamId": "jordan",
        "value": 4
      }
    ]
  },
  {
    "category": "constructors",
    "title": "Most Constructor Championships",
    "entries": [
      {
        "rank": 1,
        "teamId": "ferrari",
        "value": 16
      },
      {
        "rank": 2,
        "teamId": "mclaren",
        "value": 10
      },
      {
        "rank": 3,
        "teamId": "williams",
        "value": 9
      },
      {
        "rank": 4,
        "teamId": "mercedes",
        "value": 8
      },
      {
        "rank": 5,
        "teamId": "lotus",
        "value": 7
      },
      {
        "rank": 6,
        "teamId": "red-bull",
        "value": 6
      },
      {
        "rank": 7,
        "teamId": "brabham",
        "value": 2
      },
      {
        "rank": 8,
        "teamId": "renault",
        "value": 2
      },
      {
        "rank": 9,
        "teamId": "cooper",
        "value": 2
      },
      {
        "rank": 10,
        "teamId": "benetton",
        "value": 1
      },
      {
        "rank": 11,
        "teamId": "tyrrell",
        "value": 1
      },
      {
        "rank": 12,
        "teamId": "brm",
        "value": 1
      },
      {
        "rank": 13,
        "teamId": "matra",
        "value": 1
      },
      {
        "rank": 14,
        "teamId": "vanwall",
        "value": 1
      },
      {
        "rank": 15,
        "teamId": "brawn",
        "value": 1
      }
    ]
  },
  {
    "category": "constructors",
    "title": "Most Constructor Pole Positions",
    "entries": [
      {
        "rank": 1,
        "teamId": "ferrari",
        "value": 254
      },
      {
        "rank": 2,
        "teamId": "mclaren",
        "value": 177
      },
      {
        "rank": 3,
        "teamId": "mercedes",
        "value": 145
      },
      {
        "rank": 4,
        "teamId": "williams",
        "value": 128
      },
      {
        "rank": 5,
        "teamId": "red-bull",
        "value": 111
      },
      {
        "rank": 6,
        "teamId": "lotus",
        "value": 107
      },
      {
        "rank": 7,
        "teamId": "renault",
        "value": 51
      },
      {
        "rank": 8,
        "teamId": "brabham",
        "value": 39
      },
      {
        "rank": 9,
        "teamId": "benetton",
        "value": 15
      },
      {
        "rank": 10,
        "teamId": "tyrrell",
        "value": 14
      },
      {
        "rank": 11,
        "teamId": "alfa-romeo",
        "value": 12
      },
      {
        "rank": 12,
        "teamId": "brm",
        "value": 11
      },
      {
        "rank": 13,
        "teamId": "cooper",
        "value": 11
      },
      {
        "rank": 14,
        "teamId": "maserati",
        "value": 10
      },
      {
        "rank": 15,
        "teamId": "ligier",
        "value": 9
      },
      {
        "rank": 16,
        "teamId": "vanwall",
        "value": 7
      },
      {
        "rank": 17,
        "teamId": "kurtis-kraft",
        "value": 6
      },
      {
        "rank": 18,
        "teamId": "brawn",
        "value": 5
      },
      {
        "rank": 19,
        "teamId": "march",
        "value": 5
      },
      {
        "rank": 20,
        "teamId": "matra",
        "value": 4
      }
    ]
  },
  {
    "category": "constructors",
    "title": "Most Constructor Podiums",
    "entries": [
      {
        "rank": 1,
        "teamId": "ferrari",
        "value": 837
      },
      {
        "rank": 2,
        "teamId": "mclaren",
        "value": 558
      },
      {
        "rank": 3,
        "teamId": "williams",
        "value": 314
      },
      {
        "rank": 4,
        "teamId": "mercedes",
        "value": 312
      },
      {
        "rank": 5,
        "teamId": "red-bull",
        "value": 297
      },
      {
        "rank": 6,
        "teamId": "lotus",
        "value": 172
      },
      {
        "rank": 7,
        "teamId": "brabham",
        "value": 124
      },
      {
        "rank": 8,
        "teamId": "renault",
        "value": 103
      },
      {
        "rank": 9,
        "teamId": "benetton",
        "value": 102
      },
      {
        "rank": 10,
        "teamId": "tyrrell",
        "value": 77
      },
      {
        "rank": 11,
        "teamId": "brm",
        "value": 61
      },
      {
        "rank": 12,
        "teamId": "cooper",
        "value": 58
      },
      {
        "rank": 13,
        "teamId": "ligier",
        "value": 50
      },
      {
        "rank": 14,
        "teamId": "maserati",
        "value": 37
      },
      {
        "rank": 15,
        "teamId": "alfa-romeo",
        "value": 26
      },
      {
        "rank": 16,
        "teamId": "lotus-f1",
        "value": 25
      },
      {
        "rank": 17,
        "teamId": "matra",
        "value": 21
      },
      {
        "rank": 18,
        "teamId": "march",
        "value": 21
      },
      {
        "rank": 19,
        "teamId": "jordan",
        "value": 19
      },
      {
        "rank": 20,
        "teamId": "bmw-sauber",
        "value": 17
      }
    ]
  },
  {
    "category": "constructors",
    "title": "Most Constructor Race Entries",
    "entries": [
      {
        "rank": 1,
        "teamId": "ferrari",
        "value": 1125
      },
      {
        "rank": 2,
        "teamId": "mclaren",
        "value": 999
      },
      {
        "rank": 3,
        "teamId": "williams",
        "value": 852
      },
      {
        "rank": 4,
        "teamId": "lotus",
        "value": 493
      },
      {
        "rank": 5,
        "teamId": "tyrrell",
        "value": 433
      },
      {
        "rank": 6,
        "teamId": "red-bull",
        "value": 419
      },
      {
        "rank": 7,
        "teamId": "renault",
        "value": 403
      },
      {
        "rank": 8,
        "teamId": "brabham",
        "value": 402
      },
      {
        "rank": 9,
        "teamId": "sauber",
        "value": 395
      },
      {
        "rank": 10,
        "teamId": "minardi",
        "value": 346
      },
      {
        "rank": 11,
        "teamId": "mercedes",
        "value": 342
      },
      {
        "rank": 12,
        "teamId": "ligier",
        "value": 330
      },
      {
        "rank": 13,
        "teamId": "arrows",
        "value": 296
      },
      {
        "rank": 14,
        "teamId": "toro-rosso",
        "value": 268
      },
      {
        "rank": 15,
        "teamId": "benetton",
        "value": 260
      },
      {
        "rank": 16,
        "teamId": "jordan",
        "value": 250
      },
      {
        "rank": 17,
        "teamId": "haas",
        "value": 215
      },
      {
        "rank": 18,
        "teamId": "alfa-romeo",
        "value": 214
      },
      {
        "rank": 19,
        "teamId": "force-india",
        "value": 212
      },
      {
        "rank": 20,
        "teamId": "brm",
        "value": 208
      }
    ]
  }
]